pango_collapse/__init__.py
pango_collapse/__main__.py
pango_collapse/alias_key.json
pango_collapse/collapse.txt
pango_collapse/collapsor.py
pango_collapse/main.py
pango_collapse/utils.py
pango_collapse-0.8.2.dist-info/LICENSE
pango_collapse-0.8.2.dist-info/METADATA
pango_collapse-0.8.2.dist-info/WHEEL
pango_collapse-0.8.2.dist-info/entry_points.txt
pango_collapse-0.8.2.dist-info/RECORD
