Metadata-Version: 2.1
Name: pango-collapse
Version: 0.8.2
Summary: Collapse Pango sublineages up to user defined parent lineages.
Author: wytamma
Author-email: wytamma.wirth@me.com
Requires-Python: >=3.8,<4.0
Classifier: Programming Language :: Python :: 3
Classifier: Programming Language :: Python :: 3.8
Classifier: Programming Language :: Python :: 3.9
Classifier: Programming Language :: Python :: 3.10
Classifier: Programming Language :: Python :: 3.11
Classifier: Programming Language :: Python :: 3.12
Requires-Dist: numpy (>=1.19.5,<1.27.0)
Requires-Dist: pandas (>=1.3,<=1.5.3)
Requires-Dist: pango-aliasor (>=0.3.0,<0.4.0)
Requires-Dist: typer[all] (>=0.6.1,<0.7.0)
